<?xml version="1.0"?>
<odoo>
    <data>
        <!-- Inherit the pos.config form view -->
        <record id="pos_config_view_form_inherit_pos_cache" model="ir.ui.view">
            <field name="name">pos.config.form.inherit.pos.cache</field>
            <field name="model">pos.config</field>
            <field name="inherit_id" ref="point_of_sale.pos_config_view_form" />
            <field name="arch" type="xml">
                <!-- Find the 'other_devices' setting element and insert the new fields after it -->
                <xpath expr="//setting[@id='other_devices']" position="after">
                    <field name='oldest_cache_time'/>
                    <button name='delete_cache' type="object" string="Invalidate cache"/>
                </xpath>
            </field>
        </record>
         <record id="pos_config_view_form_inherit_pos_default_customer" model="ir.ui.view">
            <field name="name">pos.config.view.form.inherit.pos.default.customer</field>
            <field name="model">res.config.settings</field>
            <field name="inherit_id" ref="point_of_sale.res_config_settings_view_form"/>
            <field name="arch" type="xml">
                <xpath expr="//block[@id='pos_interface_section']" position="inside">
                    <setting string="Default Customer" help="Set default payment method">
                        <div class="content-group mt16">
                             <field name='oldest_cache_time'/>
                    <button name='delete_cache' type="object" string="Invalidate cache"/>
                        </div>
                    </setting>
                </xpath>
            </field>
        </record>
    </data>
</odoo>